[["Map",1,2,9,10],"meta::meta",["Map",3,4,5,6,7,8],"astro-version","5.3.0","content-config-digest","5c1034b54f8bb370","astro-config-digest","{\"root\":{},\"srcDir\":{},\"publicDir\":{},\"outDir\":{},\"cacheDir\":{},\"site\":\"https://bidspec.urbanforward.tech\",\"compressHTML\":true,\"base\":\"/\",\"trailingSlash\":\"ignore\",\"output\":\"static\",\"scopedStyleStrategy\":\"attribute\",\"build\":{\"format\":\"directory\",\"client\":{},\"server\":{},\"assets\":\"_astro\",\"serverEntry\":\"entry.mjs\",\"redirects\":true,\"inlineStylesheets\":\"auto\",\"concurrency\":1},\"server\":{\"open\":false,\"host\":false,\"port\":4321,\"streaming\":true},\"redirects\":{},\"image\":{\"endpoint\":{\"route\":\"/_image\"},\"service\":{\"entrypoint\":\"astro/assets/services/sharp\",\"config\":{}},\"domains\":[],\"remotePatterns\":[]},\"devToolbar\":{\"enabled\":true},\"markdown\":{\"syntaxHighlight\":\"shiki\",\"shikiConfig\":{\"langs\":[],\"langAlias\":{},\"theme\":\"github-dark\",\"themes\":{},\"wrap\":false,\"transformers\":[]},\"remarkPlugins\":[],\"rehypePlugins\":[],\"remarkRehype\":{},\"gfm\":true,\"smartypants\":true},\"security\":{\"checkOrigin\":true},\"env\":{\"schema\":{},\"validateSecrets\":false},\"experimental\":{\"clientPrerender\":false,\"contentIntellisense\":false,\"responsiveImages\":false,\"serializeConfig\":false},\"legacy\":{\"collections\":false}}","projects",["Map",11,12,78,79,121,122,177,178,221,222,277,278],"downtown-brooklyn",{"id":11,"data":13,"body":40,"filePath":41,"assetImports":42,"digest":44,"rendered":45,"legacyId":77},{"title":14,"description":15,"publishDate":16,"updatedDate":17,"thumbnail":18,"bidName":19,"borough":20,"yearEstablished":21,"featured":22,"revisionMode":22,"tags":23,"insightComponents":28,"transformationComponents":30,"predictionComponents":31,"consensusComponents":32,"dataSource":33,"visualizationTechniques":34},"Downtown Brooklyn Partnership","Analysis of the Downtown Brooklyn Partnership, a major commercial and cultural district in Brooklyn.",["Date","2023-10-01T00:00:00.000Z"],["Date","2023-10-15T00:00:00.000Z"],"__ASTRO_IMAGE_../../assets/placeholder.jpg","Fulton Mall Improvement Association","Brooklyn",2006,true,[24,25,26,27],"Commercial Hub","Education","Cultural District","Urban Development",[29],"/src/components/groups/_matt_demo/RobotabilityMap.jsx",[],[],[],"NYC Open Data, Downtown Brooklyn Partnership Annual Reports, Census Data, Real Estate Market Data, Transit Data, Academic Institution Statistics",[35,36,37,38,39],"Time Series Analysis","Comparative Metrics","Spatial Analysis","Economic Impact Assessment","Transit Flow Analysis","The Downtown Brooklyn Partnership manages New York City's third-largest central business district. Established in 2006, the Partnership oversees three Business Improvement Districts (MetroTech, Fulton Mall, and Court-Livingston-Schermerhorn) covering a 1.8 square mile area. The district is home to major educational institutions, cultural venues, government offices, and a growing residential population. Downtown Brooklyn has experienced significant transformation from a primarily commercial area into a mixed-use neighborhood with increasing residential development, retail options, and public space improvements.\r\n\r\n# Insight Analysis\r\n\r\nLorem ipsum dolor sit amet, consectetur adipiscing elit. Nulla facilisi. Proin eget fermentum nisi. Vestibulum ante ipsum primis in faucibus orci luctus et ultrices posuere cubilia curae; Donec euismod, nisl eget aliquam ultricies, nunc sapien ultricies arcu, vel feugiat nunc nisl eget libero. Vivamus commodo tortor ac quam varius, in accumsan nulla rutrum. Mauris egestas erat sit amet augue volutpat, eu convallis odio tincidunt. Nulla facilisi. Praesent luctus urna sed dolor congue dictum. Maecenas dignissim eros at nisi varius, in lacinia velit pulvinar.\r\n\r\nPellentesque habitant morbi tristique senectus et netus et malesuada fames ac turpis egestas. In hac habitasse platea dictumst. Proin sed finibus justo. Praesent ultrices dolor non fermentum blandit. Quisque vel congue magna, at varius ligula. Aliquam erat volutpat. Aenean vestibulum metus nec enim consequat, id maximus dolor dignissim. Nullam vehicula tristique eros, non cursus purus elementum ac. Mauris tempus erat purus, sit amet feugiat enim fermentum non.\r\n\r\n# Transformation Analysis\r\n\r\nLorem ipsum dolor sit amet, consectetur adipiscing elit. Sed eget neque at metus aliquam convallis. Nam finibus convallis felis, eu faucibus neque. Vestibulum gravida diam at ipsum posuere, ut pulvinar purus malesuada. Integer gravida fringilla arcu a fermentum. Nullam faucibus dui augue, a imperdiet magna gravida ut. Donec ac justo et enim tempus gravida at quis quam. Duis eu dapibus nisi, a fermentum quam. Mauris nec leo sit amet elit gravida egestas vel at magna. Nulla nisi neque, iaculis in augue eget, lacinia sodales nisl.\r\n\r\nMauris faucibus risus eget libero facilisis, non sagittis urna gravida. Sed feugiat justo odio, non mollis massa efficitur ac. Vestibulum ante ipsum primis in faucibus orci luctus et ultrices posuere cubilia curae; Pellentesque vulputate dictum dolor, eget vestibulum magna volutpat at. Cras a tellus velit. Nam nisi libero, aliquet at facilisis at, consequat nec purus. Sed tincidunt ligula eget placerat rutrum. Praesent pharetra congue purus, eu consequat nisl. Pellentesque euismod, mauris id ultrices efficitur, erat purus imperdiet magna, sit amet sollicitudin turpis ante id lacus.\r\n\r\n# Prediction Analysis\r\n\r\nLorem ipsum dolor sit amet, consectetur adipiscing elit. Sed feugiat lacus ut justo elementum, efficitur sollicitudin nulla volutpat. In hac habitasse platea dictumst. Ut varius at arcu vel vestibulum. Quisque congue magna a ligula elementum, sit amet eleifend eros rutrum. Donec eu nisi eu tortor posuere dictum. Quisque et fringilla justo. Nullam nec auctor nisi. Donec ornare nibh vel consequat tempus. Aliquam laoreet diam turpis, non aliquet libero convallis in. Sed facilisis, velit nec gravida dapibus, dolor felis tincidunt diam, non sagittis est nisi eget ex. Nullam eget semper erat. Vivamus viverra ac enim at tempor. Vestibulum id tellus at velit rhoncus tincidunt sed ut magna.\r\n\r\nCurabitur tincidunt felis quis dui fermentum, eget tristique erat interdum. Mauris vel leo semper, facilisis ligula vitae, porta risus. Duis facilisis purus vel ipsum maximus, nec sagittis magna facilisis. Sed arcu magna, rhoncus nec congue ut, finibus sed diam. Ut sodales tellus non ornare tempus. Donec at felis pellentesque, malesuada neque posuere, ultrices sem. Nam pharetra sapien sed eros congue, in tincidunt nisl semper. Fusce porta felis in risus molestie, vel placerat mauris facilisis.\r\n\r\n# Consensus Analysis\r\n\r\nLorem ipsum dolor sit amet, consectetur adipiscing elit. Donec et tortor eget magna consequat tincidunt. Phasellus neque nulla, finibus ac sollicitudin non, convallis vel nisi. Etiam auctor placerat faucibus. Ut vitae mollis ante, et tempus mauris. Quisque ac urna purus. Aliquam vulputate molestie lectus, non volutpat risus vehicula luctus. Aenean ac quam eu purus eleifend placerat at eget diam. Morbi dapibus at elit in convallis. Mauris posuere leo quam, vitae fringilla leo tempor vel. Ut quis mi porta, suscipit ligula ac, consequat leo. Cras id imperdiet lectus. Aenean quis arcu nisi. Nulla vel nisl eu eros finibus auctor ac ut urna. Suspendisse ac luctus arcu.\r\n\r\nDonec vitae justo vitae turpis rutrum vestibulum vel at tortor. Aliquam quis tellus ut quam viverra fermentum in vitae nulla. Sed mattis accumsan libero, vel sollicitudin ante fringilla at. Nulla facilisi. Duis dignissim varius est, nec dignissim eros. Nullam orci risus, fermentum eu faucibus sit amet, laoreet quis eros. Proin bibendum, metus id bibendum pretium, quam urna dapibus leo, eget tempor magna sem at purus. Praesent faucibus dui id varius elementum. Sed consectetur, orci id rhoncus eleifend, enim magna pellentesque ante, et ornare lectus diam sit amet diam. Integer at magna et arcu iaculis consectetur at dictum lacus.\r\n\r\n## Additional Resources\r\n\r\n- [Downtown Brooklyn Partnership Website](https://www.downtownbrooklyn.com/)\r\n- [Annual Report (PDF)](https://www.downtownbrooklyn.com/about/annual-reports)\r\n- [NYC Small Business Services - BID Directory](https://www1.nyc.gov/site/sbs/neighborhoods/business-improvement-districts.page)","src/content/projects/downtown-brooklyn.md",[43],"../../assets/placeholder.jpg","1f62fc4571836dcb",{"html":46,"metadata":47},"\u003Cp>The Downtown Brooklyn Partnership manages New York City’s third-largest central business district. Established in 2006, the Partnership oversees three Business Improvement Districts (MetroTech, Fulton Mall, and Court-Livingston-Schermerhorn) covering a 1.8 square mile area. The district is home to major educational institutions, cultural venues, government offices, and a growing residential population. Downtown Brooklyn has experienced significant transformation from a primarily commercial area into a mixed-use neighborhood with increasing residential development, retail options, and public space improvements.\u003C/p>\n\u003Ch1 id=\"insight-analysis\">Insight Analysis\u003C/h1>\n\u003Cp>Lorem ipsum dolor sit amet, consectetur adipiscing elit. Nulla facilisi. Proin eget fermentum nisi. Vestibulum ante ipsum primis in faucibus orci luctus et ultrices posuere cubilia curae; Donec euismod, nisl eget aliquam ultricies, nunc sapien ultricies arcu, vel feugiat nunc nisl eget libero. Vivamus commodo tortor ac quam varius, in accumsan nulla rutrum. Mauris egestas erat sit amet augue volutpat, eu convallis odio tincidunt. Nulla facilisi. Praesent luctus urna sed dolor congue dictum. Maecenas dignissim eros at nisi varius, in lacinia velit pulvinar.\u003C/p>\n\u003Cp>Pellentesque habitant morbi tristique senectus et netus et malesuada fames ac turpis egestas. In hac habitasse platea dictumst. Proin sed finibus justo. Praesent ultrices dolor non fermentum blandit. Quisque vel congue magna, at varius ligula. Aliquam erat volutpat. Aenean vestibulum metus nec enim consequat, id maximus dolor dignissim. Nullam vehicula tristique eros, non cursus purus elementum ac. Mauris tempus erat purus, sit amet feugiat enim fermentum non.\u003C/p>\n\u003Ch1 id=\"transformation-analysis\">Transformation Analysis\u003C/h1>\n\u003Cp>Lorem ipsum dolor sit amet, consectetur adipiscing elit. Sed eget neque at metus aliquam convallis. Nam finibus convallis felis, eu faucibus neque. Vestibulum gravida diam at ipsum posuere, ut pulvinar purus malesuada. Integer gravida fringilla arcu a fermentum. Nullam faucibus dui augue, a imperdiet magna gravida ut. Donec ac justo et enim tempus gravida at quis quam. Duis eu dapibus nisi, a fermentum quam. Mauris nec leo sit amet elit gravida egestas vel at magna. Nulla nisi neque, iaculis in augue eget, lacinia sodales nisl.\u003C/p>\n\u003Cp>Mauris faucibus risus eget libero facilisis, non sagittis urna gravida. Sed feugiat justo odio, non mollis massa efficitur ac. Vestibulum ante ipsum primis in faucibus orci luctus et ultrices posuere cubilia curae; Pellentesque vulputate dictum dolor, eget vestibulum magna volutpat at. Cras a tellus velit. Nam nisi libero, aliquet at facilisis at, consequat nec purus. Sed tincidunt ligula eget placerat rutrum. Praesent pharetra congue purus, eu consequat nisl. Pellentesque euismod, mauris id ultrices efficitur, erat purus imperdiet magna, sit amet sollicitudin turpis ante id lacus.\u003C/p>\n\u003Ch1 id=\"prediction-analysis\">Prediction Analysis\u003C/h1>\n\u003Cp>Lorem ipsum dolor sit amet, consectetur adipiscing elit. Sed feugiat lacus ut justo elementum, efficitur sollicitudin nulla volutpat. In hac habitasse platea dictumst. Ut varius at arcu vel vestibulum. Quisque congue magna a ligula elementum, sit amet eleifend eros rutrum. Donec eu nisi eu tortor posuere dictum. Quisque et fringilla justo. Nullam nec auctor nisi. Donec ornare nibh vel consequat tempus. Aliquam laoreet diam turpis, non aliquet libero convallis in. Sed facilisis, velit nec gravida dapibus, dolor felis tincidunt diam, non sagittis est nisi eget ex. Nullam eget semper erat. Vivamus viverra ac enim at tempor. Vestibulum id tellus at velit rhoncus tincidunt sed ut magna.\u003C/p>\n\u003Cp>Curabitur tincidunt felis quis dui fermentum, eget tristique erat interdum. Mauris vel leo semper, facilisis ligula vitae, porta risus. Duis facilisis purus vel ipsum maximus, nec sagittis magna facilisis. Sed arcu magna, rhoncus nec congue ut, finibus sed diam. Ut sodales tellus non ornare tempus. Donec at felis pellentesque, malesuada neque posuere, ultrices sem. Nam pharetra sapien sed eros congue, in tincidunt nisl semper. Fusce porta felis in risus molestie, vel placerat mauris facilisis.\u003C/p>\n\u003Ch1 id=\"consensus-analysis\">Consensus Analysis\u003C/h1>\n\u003Cp>Lorem ipsum dolor sit amet, consectetur adipiscing elit. Donec et tortor eget magna consequat tincidunt. Phasellus neque nulla, finibus ac sollicitudin non, convallis vel nisi. Etiam auctor placerat faucibus. Ut vitae mollis ante, et tempus mauris. Quisque ac urna purus. Aliquam vulputate molestie lectus, non volutpat risus vehicula luctus. Aenean ac quam eu purus eleifend placerat at eget diam. Morbi dapibus at elit in convallis. Mauris posuere leo quam, vitae fringilla leo tempor vel. Ut quis mi porta, suscipit ligula ac, consequat leo. Cras id imperdiet lectus. Aenean quis arcu nisi. Nulla vel nisl eu eros finibus auctor ac ut urna. Suspendisse ac luctus arcu.\u003C/p>\n\u003Cp>Donec vitae justo vitae turpis rutrum vestibulum vel at tortor. Aliquam quis tellus ut quam viverra fermentum in vitae nulla. Sed mattis accumsan libero, vel sollicitudin ante fringilla at. Nulla facilisi. Duis dignissim varius est, nec dignissim eros. Nullam orci risus, fermentum eu faucibus sit amet, laoreet quis eros. Proin bibendum, metus id bibendum pretium, quam urna dapibus leo, eget tempor magna sem at purus. Praesent faucibus dui id varius elementum. Sed consectetur, orci id rhoncus eleifend, enim magna pellentesque ante, et ornare lectus diam sit amet diam. Integer at magna et arcu iaculis consectetur at dictum lacus.\u003C/p>\n\u003Ch2 id=\"additional-resources\">Additional Resources\u003C/h2>\n\u003Cul>\n\u003Cli>\u003Ca href=\"https://www.downtownbrooklyn.com/\">Downtown Brooklyn Partnership Website\u003C/a>\u003C/li>\n\u003Cli>\u003Ca href=\"https://www.downtownbrooklyn.com/about/annual-reports\">Annual Report (PDF)\u003C/a>\u003C/li>\n\u003Cli>\u003Ca href=\"https://www1.nyc.gov/site/sbs/neighborhoods/business-improvement-districts.page\">NYC Small Business Services - BID Directory\u003C/a>\u003C/li>\n\u003C/ul>",{"headings":48,"imagePaths":66,"frontmatter":67},[49,53,56,59,62],{"depth":50,"slug":51,"text":52},1,"insight-analysis","Insight Analysis",{"depth":50,"slug":54,"text":55},"transformation-analysis","Transformation Analysis",{"depth":50,"slug":57,"text":58},"prediction-analysis","Prediction Analysis",{"depth":50,"slug":60,"text":61},"consensus-analysis","Consensus Analysis",{"depth":63,"slug":64,"text":65},2,"additional-resources","Additional Resources",[],{"title":14,"description":15,"publishDate":68,"updatedDate":69,"thumbnail":43,"bidName":19,"borough":20,"yearEstablished":21,"featured":22,"draft":70,"revisionMode":22,"tags":71,"insightComponents":72,"transformationComponents":73,"predictionComponents":74,"consensusComponents":75,"dataSource":33,"visualizationTechniques":76},["Date","2023-10-01T00:00:00.000Z"],["Date","2023-10-15T00:00:00.000Z"],false,[24,25,26,27],[29],[],[],[],[35,36,37,38,39],"downtown-brooklyn.md","fifth-avenue-brooklyn",{"id":78,"data":80,"body":97,"filePath":98,"assetImports":99,"digest":100,"rendered":101,"legacyId":120},{"title":81,"description":82,"publishDate":83,"updatedDate":84,"thumbnail":18,"bidName":85,"borough":20,"yearEstablished":86,"featured":22,"revisionMode":22,"tags":87,"insightComponents":91,"transformationComponents":92,"predictionComponents":93,"consensusComponents":94,"dataSource":95,"visualizationTechniques":96},"5th Avenue BID - Brooklyn","Analysis of the 5th Avenue Business Improvement District in Park Slope, Brooklyn.",["Date","2023-09-15T00:00:00.000Z"],["Date","2023-10-01T00:00:00.000Z"],"Park Slope 5th Avenue",1992,[88,89,90],"Retail","Small Business","Community Development",[],[],[],[],"NYC Open Data, 5th Avenue BID Annual Reports, Census Data",[35,36],"The 5th Avenue Business Improvement District serves one of Brooklyn's most vibrant commercial corridors in Park Slope. Established in 1992, the BID supports approximately 500 businesses along a 1.5-mile stretch of 5th Avenue from Dean Street to 18th Street. The district is known for its eclectic mix of independent retailers, restaurants, and service businesses.\r\n\r\n# Insight Analysis\r\n\r\nLorem ipsum dolor sit amet, consectetur adipiscing elit. Nulla facilisi. Proin eget fermentum nisi. Vestibulum ante ipsum primis in faucibus orci luctus et ultrices posuere cubilia curae; Donec euismod, nisl eget aliquam ultricies, nunc sapien ultricies arcu, vel feugiat nunc nisl eget libero. Vivamus commodo tortor ac quam varius, in accumsan nulla rutrum. Mauris egestas erat sit amet augue volutpat, eu convallis odio tincidunt. Nulla facilisi. Praesent luctus urna sed dolor congue dictum. Maecenas dignissim eros at nisi varius, in lacinia velit pulvinar.\r\n\r\nPellentesque habitant morbi tristique senectus et netus et malesuada fames ac turpis egestas. In hac habitasse platea dictumst. Proin sed finibus justo. Praesent ultrices dolor non fermentum blandit. Quisque vel congue magna, at varius ligula. Aliquam erat volutpat. Aenean vestibulum metus nec enim consequat, id maximus dolor dignissim. Nullam vehicula tristique eros, non cursus purus elementum ac. Mauris tempus erat purus, sit amet feugiat enim fermentum non.\r\n\r\n# Transformation Analysis\r\n\r\nLorem ipsum dolor sit amet, consectetur adipiscing elit. Sed eget neque at metus aliquam convallis. Nam finibus convallis felis, eu faucibus neque. Vestibulum gravida diam at ipsum posuere, ut pulvinar purus malesuada. Integer gravida fringilla arcu a fermentum. Nullam faucibus dui augue, a imperdiet magna gravida ut. Donec ac justo et enim tempus gravida at quis quam. Duis eu dapibus nisi, a fermentum quam. Mauris nec leo sit amet elit gravida egestas vel at magna. Nulla nisi neque, iaculis in augue eget, lacinia sodales nisl.\r\n\r\nMauris faucibus risus eget libero facilisis, non sagittis urna gravida. Sed feugiat justo odio, non mollis massa efficitur ac. Vestibulum ante ipsum primis in faucibus orci luctus et ultrices posuere cubilia curae; Pellentesque vulputate dictum dolor, eget vestibulum magna volutpat at. Cras a tellus velit. Nam nisi libero, aliquet at facilisis at, consequat nec purus. Sed tincidunt ligula eget placerat rutrum. Praesent pharetra congue purus, eu consequat nisl. Pellentesque euismod, mauris id ultrices efficitur, erat purus imperdiet magna, sit amet sollicitudin turpis ante id lacus.\r\n\r\n# Prediction Analysis\r\n\r\nLorem ipsum dolor sit amet, consectetur adipiscing elit. Sed feugiat lacus ut justo elementum, efficitur sollicitudin nulla volutpat. In hac habitasse platea dictumst. Ut varius at arcu vel vestibulum. Quisque congue magna a ligula elementum, sit amet eleifend eros rutrum. Donec eu nisi eu tortor posuere dictum. Quisque et fringilla justo. Nullam nec auctor nisi. Donec ornare nibh vel consequat tempus. Aliquam laoreet diam turpis, non aliquet libero convallis in. Sed facilisis, velit nec gravida dapibus, dolor felis tincidunt diam, non sagittis est nisi eget ex. Nullam eget semper erat. Vivamus viverra ac enim at tempor. Vestibulum id tellus at velit rhoncus tincidunt sed ut magna.\r\n\r\nCurabitur tincidunt felis quis dui fermentum, eget tristique erat interdum. Mauris vel leo semper, facilisis ligula vitae, porta risus. Duis facilisis purus vel ipsum maximus, nec sagittis magna facilisis. Sed arcu magna, rhoncus nec congue ut, finibus sed diam. Ut sodales tellus non ornare tempus. Donec at felis pellentesque, malesuada neque posuere, ultrices sem. Nam pharetra sapien sed eros congue, in tincidunt nisl semper. Fusce porta felis in risus molestie, vel placerat mauris facilisis.\r\n\r\n# Consensus Analysis\r\n\r\nLorem ipsum dolor sit amet, consectetur adipiscing elit. Donec et tortor eget magna consequat tincidunt. Phasellus neque nulla, finibus ac sollicitudin non, convallis vel nisi. Etiam auctor placerat faucibus. Ut vitae mollis ante, et tempus mauris. Quisque ac urna purus. Aliquam vulputate molestie lectus, non volutpat risus vehicula luctus. Aenean ac quam eu purus eleifend placerat at eget diam. Morbi dapibus at elit in convallis. Mauris posuere leo quam, vitae fringilla leo tempor vel. Ut quis mi porta, suscipit ligula ac, consequat leo. Cras id imperdiet lectus. Aenean quis arcu nisi. Nulla vel nisl eu eros finibus auctor ac ut urna. Suspendisse ac luctus arcu.\r\n\r\nDonec vitae justo vitae turpis rutrum vestibulum vel at tortor. Aliquam quis tellus ut quam viverra fermentum in vitae nulla. Sed mattis accumsan libero, vel sollicitudin ante fringilla at. Nulla facilisi. Duis dignissim varius est, nec dignissim eros. Nullam orci risus, fermentum eu faucibus sit amet, laoreet quis eros. Proin bibendum, metus id bibendum pretium, quam urna dapibus leo, eget tempor magna sem at purus. Praesent faucibus dui id varius elementum. Sed consectetur, orci id rhoncus eleifend, enim magna pellentesque ante, et ornare lectus diam sit amet diam. Integer at magna et arcu iaculis consectetur at dictum lacus.\r\n\r\n## Additional Resources\r\n\r\n- [5th Avenue BID Website](https://parkslopefifthavenuebid.com/)\r\n- [Annual Report (PDF)](https://parkslopefifthavenuebid.com/annual-reports/)\r\n- [NYC Small Business Services - BID Directory](https://www1.nyc.gov/site/sbs/neighborhoods/business-improvement-districts.page)","src/content/projects/fifth-avenue-brooklyn.md",[43],"40ca992662ff1167",{"html":102,"metadata":103},"\u003Cp>The 5th Avenue Business Improvement District serves one of Brooklyn’s most vibrant commercial corridors in Park Slope. Established in 1992, the BID supports approximately 500 businesses along a 1.5-mile stretch of 5th Avenue from Dean Street to 18th Street. The district is known for its eclectic mix of independent retailers, restaurants, and service businesses.\u003C/p>\n\u003Ch1 id=\"insight-analysis\">Insight Analysis\u003C/h1>\n\u003Cp>Lorem ipsum dolor sit amet, consectetur adipiscing elit. Nulla facilisi. Proin eget fermentum nisi. Vestibulum ante ipsum primis in faucibus orci luctus et ultrices posuere cubilia curae; Donec euismod, nisl eget aliquam ultricies, nunc sapien ultricies arcu, vel feugiat nunc nisl eget libero. Vivamus commodo tortor ac quam varius, in accumsan nulla rutrum. Mauris egestas erat sit amet augue volutpat, eu convallis odio tincidunt. Nulla facilisi. Praesent luctus urna sed dolor congue dictum. Maecenas dignissim eros at nisi varius, in lacinia velit pulvinar.\u003C/p>\n\u003Cp>Pellentesque habitant morbi tristique senectus et netus et malesuada fames ac turpis egestas. In hac habitasse platea dictumst. Proin sed finibus justo. Praesent ultrices dolor non fermentum blandit. Quisque vel congue magna, at varius ligula. Aliquam erat volutpat. Aenean vestibulum metus nec enim consequat, id maximus dolor dignissim. Nullam vehicula tristique eros, non cursus purus elementum ac. Mauris tempus erat purus, sit amet feugiat enim fermentum non.\u003C/p>\n\u003Ch1 id=\"transformation-analysis\">Transformation Analysis\u003C/h1>\n\u003Cp>Lorem ipsum dolor sit amet, consectetur adipiscing elit. Sed eget neque at metus aliquam convallis. Nam finibus convallis felis, eu faucibus neque. Vestibulum gravida diam at ipsum posuere, ut pulvinar purus malesuada. Integer gravida fringilla arcu a fermentum. Nullam faucibus dui augue, a imperdiet magna gravida ut. Donec ac justo et enim tempus gravida at quis quam. Duis eu dapibus nisi, a fermentum quam. Mauris nec leo sit amet elit gravida egestas vel at magna. Nulla nisi neque, iaculis in augue eget, lacinia sodales nisl.\u003C/p>\n\u003Cp>Mauris faucibus risus eget libero facilisis, non sagittis urna gravida. Sed feugiat justo odio, non mollis massa efficitur ac. Vestibulum ante ipsum primis in faucibus orci luctus et ultrices posuere cubilia curae; Pellentesque vulputate dictum dolor, eget vestibulum magna volutpat at. Cras a tellus velit. Nam nisi libero, aliquet at facilisis at, consequat nec purus. Sed tincidunt ligula eget placerat rutrum. Praesent pharetra congue purus, eu consequat nisl. Pellentesque euismod, mauris id ultrices efficitur, erat purus imperdiet magna, sit amet sollicitudin turpis ante id lacus.\u003C/p>\n\u003Ch1 id=\"prediction-analysis\">Prediction Analysis\u003C/h1>\n\u003Cp>Lorem ipsum dolor sit amet, consectetur adipiscing elit. Sed feugiat lacus ut justo elementum, efficitur sollicitudin nulla volutpat. In hac habitasse platea dictumst. Ut varius at arcu vel vestibulum. Quisque congue magna a ligula elementum, sit amet eleifend eros rutrum. Donec eu nisi eu tortor posuere dictum. Quisque et fringilla justo. Nullam nec auctor nisi. Donec ornare nibh vel consequat tempus. Aliquam laoreet diam turpis, non aliquet libero convallis in. Sed facilisis, velit nec gravida dapibus, dolor felis tincidunt diam, non sagittis est nisi eget ex. Nullam eget semper erat. Vivamus viverra ac enim at tempor. Vestibulum id tellus at velit rhoncus tincidunt sed ut magna.\u003C/p>\n\u003Cp>Curabitur tincidunt felis quis dui fermentum, eget tristique erat interdum. Mauris vel leo semper, facilisis ligula vitae, porta risus. Duis facilisis purus vel ipsum maximus, nec sagittis magna facilisis. Sed arcu magna, rhoncus nec congue ut, finibus sed diam. Ut sodales tellus non ornare tempus. Donec at felis pellentesque, malesuada neque posuere, ultrices sem. Nam pharetra sapien sed eros congue, in tincidunt nisl semper. Fusce porta felis in risus molestie, vel placerat mauris facilisis.\u003C/p>\n\u003Ch1 id=\"consensus-analysis\">Consensus Analysis\u003C/h1>\n\u003Cp>Lorem ipsum dolor sit amet, consectetur adipiscing elit. Donec et tortor eget magna consequat tincidunt. Phasellus neque nulla, finibus ac sollicitudin non, convallis vel nisi. Etiam auctor placerat faucibus. Ut vitae mollis ante, et tempus mauris. Quisque ac urna purus. Aliquam vulputate molestie lectus, non volutpat risus vehicula luctus. Aenean ac quam eu purus eleifend placerat at eget diam. Morbi dapibus at elit in convallis. Mauris posuere leo quam, vitae fringilla leo tempor vel. Ut quis mi porta, suscipit ligula ac, consequat leo. Cras id imperdiet lectus. Aenean quis arcu nisi. Nulla vel nisl eu eros finibus auctor ac ut urna. Suspendisse ac luctus arcu.\u003C/p>\n\u003Cp>Donec vitae justo vitae turpis rutrum vestibulum vel at tortor. Aliquam quis tellus ut quam viverra fermentum in vitae nulla. Sed mattis accumsan libero, vel sollicitudin ante fringilla at. Nulla facilisi. Duis dignissim varius est, nec dignissim eros. Nullam orci risus, fermentum eu faucibus sit amet, laoreet quis eros. Proin bibendum, metus id bibendum pretium, quam urna dapibus leo, eget tempor magna sem at purus. Praesent faucibus dui id varius elementum. Sed consectetur, orci id rhoncus eleifend, enim magna pellentesque ante, et ornare lectus diam sit amet diam. Integer at magna et arcu iaculis consectetur at dictum lacus.\u003C/p>\n\u003Ch2 id=\"additional-resources\">Additional Resources\u003C/h2>\n\u003Cul>\n\u003Cli>\u003Ca href=\"https://parkslopefifthavenuebid.com/\">5th Avenue BID Website\u003C/a>\u003C/li>\n\u003Cli>\u003Ca href=\"https://parkslopefifthavenuebid.com/annual-reports/\">Annual Report (PDF)\u003C/a>\u003C/li>\n\u003Cli>\u003Ca href=\"https://www1.nyc.gov/site/sbs/neighborhoods/business-improvement-districts.page\">NYC Small Business Services - BID Directory\u003C/a>\u003C/li>\n\u003C/ul>",{"headings":104,"imagePaths":110,"frontmatter":111},[105,106,107,108,109],{"depth":50,"slug":51,"text":52},{"depth":50,"slug":54,"text":55},{"depth":50,"slug":57,"text":58},{"depth":50,"slug":60,"text":61},{"depth":63,"slug":64,"text":65},[],{"title":81,"description":82,"publishDate":112,"updatedDate":113,"thumbnail":43,"bidName":85,"borough":20,"yearEstablished":86,"featured":22,"draft":70,"revisionMode":22,"tags":114,"insightComponents":115,"transformationComponents":116,"predictionComponents":117,"consensusComponents":118,"dataSource":95,"visualizationTechniques":119},["Date","2023-09-15T00:00:00.000Z"],["Date","2023-10-01T00:00:00.000Z"],[88,89,90],[],[],[],[],[35,36],"fifth-avenue-brooklyn.md","dumbo",{"id":121,"data":123,"body":147,"filePath":148,"assetImports":149,"digest":150,"rendered":151,"legacyId":176},{"title":124,"description":125,"publishDate":126,"updatedDate":127,"thumbnail":18,"bidName":128,"borough":20,"yearEstablished":21,"featured":22,"revisionMode":22,"tags":129,"insightComponents":134,"transformationComponents":137,"predictionComponents":139,"consensusComponents":142,"dataSource":145,"visualizationTechniques":146},"DUMBO Improvement District","Analysis of the DUMBO Improvement District in Brooklyn, an area known for its tech innovation and arts scene.",["Date","2023-09-25T00:00:00.000Z"],["Date","2023-10-10T00:00:00.000Z"],"DUMBO",[130,131,132,133],"Tech Hub","Arts","Waterfront","Historic Industrial",[135,136],"/components/groups/dumbo/york st station.JPG","/components/groups/dumbo/dock st.JPG",[138],"/components/groups/dumbo/trail.png",[140,141],"https://www.youtube.com/embed/rHzQ4340RnY","https://www.youtube.com/embed/I_0m2gpL_gE",[143,144],"/components/groups/dumbo/consensus 1.png","/components/groups/dumbo/consensus 2.png","NYC Open Data, DUMBO Improvement District Annual Reports, Census Data, Real Estate Market Data, Tourism Statistics",[35,36,37,38],"Our project addresses the unique challenges facing one of Brooklyn’s most iconic neighborhoods. As a historic industrial district transformed into a thriving tech and creative hub, DUMBO suffers from extreme visitor concentration at a single photo location while many of its cultural and commercial assets remain underutilized. \r\n\r\nOur approach tackles this imbalance through strategic interventions that redistribute foot traffic, enhance the pedestrian experience, and activate underused public spaces. Based on interviews with residents, business owners, and visitors, we’ve developed solutions that benefit all stakeholders while preserving DUMBO’s distinctive character. \r\n\r\nOne of the project’s transformations is the DUMBO Discovery Trail, a self-guided walking path connecting scenic views, cultural landmarks, and local businesses throughout the district. Complemented by targeted streetscape enhancements and strategic activation of underutilized spaces, our plan creates a more balanced, engaging, and economically vibrant neighborhood experience. \r\n\r\nKey Facts: \r\n- Location: DUMBO (Down Under the Manhattan Bridge Overpass), Brooklyn, NY\r\nChallenge: 80% of visitors cluster at one photo spot (Washington St), straining infrastructure and limiting neighborhood exploration \r\n- Economic Context: Median income $163K (vs. NYC’s average of $55K)\r\n- Neighborhood Assets: Iconic bridge views, cobblestone streets, 140+ art studios/galleries, Brooklyn Tech Triangle anchor (1,000+ tech firms) \r\n- Project Goal: Disperse tourist traffic, enhance the pedestrian experience, and activate underused public space \r\n![overview](/public/components/groups/dumbo/overview.jpg)\r\n\r\n\r\n# Insight Analysis\r\n\r\nThrough interviews with tourists, local businesses, and visitors, research, and field visit to DUMBO, we observed a significant imbalance in how people experience the neighborhood, with most visitors gravitating to a single attraction while missing the area’s rich diversity. \r\n\r\nWashington Street’s famous Manhattan Bridge view has become a victim of its own Instagram success, creating severe bottlenecks that disrupt pedestrian flow and overwhelm local infrastructure. During peak hours, the concentration of tourists and photographers creates a congested environment that diminishes the experience for everyone. This over-concentration demonstrates a missed opportunity, as many visitors leave without experiencing DUMBO’s broader offerings. \r\n\r\n![washington](/public/components/groups/dumbo/Washington%20St.JPG)\r\n\r\nMeanwhile, several potentially vibrant public spaces throughout the district sit underutilized. Areas like Dock Street, Anchorage Plaza, and the York Street subway entrance lack distinctive identity and programming, appearing as “dead zones” to visitors with no compelling reason to linger. These spaces have tremendous potential for activation through strategic interventions such as seating, public art, and temporary markets that could transform them into worthy destinations. \r\n\r\nThe absence of an intuitive wayfinding system compounds these issues. Without clear signage or suggested routes, visitors struggle to discover attractions beyond Washington Street. Cultural venues, local businesses, and alternative viewpoints remain hidden gems, unknown to most tourists who visit. This navigation challenge prevents organic exploration and limits economic benefits from spreading throughout the neighborhood. \r\n\r\nUltimately, DUMBO’s fundamental challenge is a disconnected visitor experience where scenic spots, shops, and cultural sites exist in isolation rather than as part of a cohesive journey. This fragmentation stems from a mismatch between the neighborhood’s potential (its diverse assets) and current perception (as a single-photo destination). Our interventions, therefore, focus on redistributing visitor density, enhancing physical and digital connectivity, and creating compelling reasons for exploration throughout the district. \r\n\r\n\r\n# Transformation Analysis\r\n\r\nBased on our insights, our transformation aims at addressing DUMBO’s issues of tourist congestion, underutilized public spaces, and fragmented visitor experiences. We proposed two main transformations: the DUMBO discovery trail and streetscape enhancements. \r\n\r\nThe first transformation is the creation of the DUMBO discovery trail. This is a self-guided walking path that links scenic views, cultural landmarks, small businesses, and art installations. The aim of this transformation is to disperse tourists beyond Washington Street by offering an intuitive, enriched, and more comprehensive exploration experience. There will be navigational signage and markers with QR codes to offer navigation assistance, historical context. There will also be seasonal themes (such as food, art, or heritage) that will encourage repeat visits. More importantly, the trail will also be integrated into major digital mapping platforms (e.g., Google Maps, Apple Maps), so visitors naturally encounter the trail when they open their apps in DUMBO. This multi-layered approach both physically and digitally weaves together DUMBO’s diverse attractions into a more cohesive journey that highlights DUMBO’s artistic characteristics and supports local business, while dispersing the tourist traffic on Washington Street. \r\n\r\nThe second transformation focuses on streetscape enhancements in underused areas such as Dock Street, Anchorage Plaza, Water & Adams Street, and the York Street Subway entrance. These spaces currently lack comfort, events, and do not look as appealing as other areas in DUMBO. The streetscape enhancements include widening sidewalks, adding seating, integrating more planters, and creating flexible open spaces for rotating public art, performances, and markets. The design language will draw from DUMBO’s industrial heritage, using cobblestones, and materials like weathered steel and bricks, to ensure that improvements reinforce the neighborhood’s unique industrial identity. Furthermore, the addition of more art pieces will help reinforce DUMBO’s identity as a creative district. The goal is to make these currently underutilized spaces more comfortable, visually cohesive, and attractive to both visitors and residents, effectively transforming “dead zones” into vibrant secondary destinations.\r\n\r\nTogether, these transformations aim to redistribute foot traffic across DUMBO, enhance visitor engagement, support local businesses, and reinforce the area’s cultural and historical character, creating a richer and more sustainable urban experience.\r\n\r\n\r\n# Prediction Analysis\r\n\r\nTo evaluate the effectiveness of our proposed crowd intervention strategies, we developed an agent-based simulation model using the GAMA platform to replicate tourist movement patterns in the DUMBO area. In the simulation, tourists enter the neighborhood from predefined entry points such as the subway station or Brooklyn Bridge, and proceed to explore the area based on their assigned behavioral profiles. Some tourists head directly to popular photo spots like the Manhattan Bridge, while others wander more randomly or follow interest-based paths. The model integrates real-world spatial data, including shapefiles for roads and buildings, and incorporates network-based pathfinding to ensure realistic movement along streets. By comparing scenarios with and without interventions—such as the addition of new attractions—we assessed the impact of these strategies on crowd distribution. The simulation results demonstrate that our intervention significantly dispersed tourist flows, reducing congestion at overly crowded landmarks and promoting a more balanced spatial distribution.\r\n\r\n# Consensus Analysis\r\n\r\n## Stakeholder Survey Engagement\r\nTo evaluate our transformation proposals with real stakeholders, we conducted on-site fieldwork in DUMBO again and asked 40 participants to do a survey. The participants included visitors, local business owners, and residents. The main part of the survey was to evaluate current and transformed spaces based on the before-and-after images. \r\n\r\nThe survey results strongly validated our design direction. Transformed locations consistently received higher appeal scores than their current state. For example, the Water & Adams area improvement shows the most dramatic increase (from 2.9 to 4.5 on a 5-point scale). The majority of participants expressed a preference for wandering and exploring different parts of DUMBO rather than visiting only the famous photo spot, supporting our Discovery Trail concept. \r\n\r\n\r\nWe also gained valuable insights into visitor types, with the data showing a diverse mix of sightseers (30.8%), culture and history enthusiasts (15.4%), food explorers (10.3%), and other categories that help calibrate our activation strategies. This real-world feedback provided empirical support for our hypothesis that visitors would enjoy a more distributed experience throughout DUMBO if appropriate infrastructure and wayfinding were in place. \r\n\r\n\r\nThe survey data will serve as a powerful communication tool in our broader consensus-building efforts. We can present visual preference results to the DUMBO BID and NYC agencies to demonstrate public support, share tourist type data with local businesses to highlight economic benefits, and use the findings as a baseline for continued engagement throughout implementation. \r\n\r\n## Broader Stakeholder Strategy\r\nBeyond our survey work, we identified key stakeholders whose input and support are essential for successful implementation, including: \r\n- DUMBO BID: Core implementation partner; coordinates with businesses, manages public space programming\r\n- NYC DOT & DCP: Infrastructure approvals, street design changes, signage, and sidewalk updates\r\n- Local Business Owners: Can help offer incentives, co-host events \r\n- Residents: Community stewards vital for long-term support and maintenance \r\n- Tourists & Visitors: End users whose behavior drives the success of the public space enhancements \r\n\r\nOur collaborative process will follow a four-stage approach: \r\n- Share & Visualize the Proposal: Present the Insight, Transformation, and Prediction narrative using visuals to make ideas clear for all audiences \r\n- Engage Stakeholders in Dialogue: Host workshops to gather input and surface priorities\r\n- Collect Public Feedback: Use QR codes, surveys, and comment boards at proposed sites\r\n- Prioritize & Adapt: Synthesize feedback to refine proposals and create a shared action plan \r\n\r\n\r\n## Additional Resources\r\n\r\n- [DUMBO Improvement District Website](https://dumbo.org/)\r\n- [Annual Report (PDF)](https://dumbo.org/annual-reports/)\r\n- [NYC Small Business Services - BID Directory](https://www1.nyc.gov/site/sbs/neighborhoods/business-improvement-districts.page)","src/content/projects/dumbo.md",[43],"71b43c5db101eff2",{"html":152,"metadata":153},"\u003Cp>Our project addresses the unique challenges facing one of Brooklyn’s most iconic neighborhoods. As a historic industrial district transformed into a thriving tech and creative hub, DUMBO suffers from extreme visitor concentration at a single photo location while many of its cultural and commercial assets remain underutilized.\u003C/p>\n\u003Cp>Our approach tackles this imbalance through strategic interventions that redistribute foot traffic, enhance the pedestrian experience, and activate underused public spaces. Based on interviews with residents, business owners, and visitors, we’ve developed solutions that benefit all stakeholders while preserving DUMBO’s distinctive character.\u003C/p>\n\u003Cp>One of the project’s transformations is the DUMBO Discovery Trail, a self-guided walking path connecting scenic views, cultural landmarks, and local businesses throughout the district. Complemented by targeted streetscape enhancements and strategic activation of underutilized spaces, our plan creates a more balanced, engaging, and economically vibrant neighborhood experience.\u003C/p>\n\u003Cp>Key Facts:\u003C/p>\n\u003Cul>\n\u003Cli>Location: DUMBO (Down Under the Manhattan Bridge Overpass), Brooklyn, NY\r\nChallenge: 80% of visitors cluster at one photo spot (Washington St), straining infrastructure and limiting neighborhood exploration\u003C/li>\n\u003Cli>Economic Context: Median income $163K (vs. NYC’s average of $55K)\u003C/li>\n\u003Cli>Neighborhood Assets: Iconic bridge views, cobblestone streets, 140+ art studios/galleries, Brooklyn Tech Triangle anchor (1,000+ tech firms)\u003C/li>\n\u003Cli>Project Goal: Disperse tourist traffic, enhance the pedestrian experience, and activate underused public space\r\n\u003Cimg src=\"/public/components/groups/dumbo/overview.jpg\" alt=\"overview\">\u003C/li>\n\u003C/ul>\n\u003Ch1 id=\"insight-analysis\">Insight Analysis\u003C/h1>\n\u003Cp>Through interviews with tourists, local businesses, and visitors, research, and field visit to DUMBO, we observed a significant imbalance in how people experience the neighborhood, with most visitors gravitating to a single attraction while missing the area’s rich diversity.\u003C/p>\n\u003Cp>Washington Street’s famous Manhattan Bridge view has become a victim of its own Instagram success, creating severe bottlenecks that disrupt pedestrian flow and overwhelm local infrastructure. During peak hours, the concentration of tourists and photographers creates a congested environment that diminishes the experience for everyone. This over-concentration demonstrates a missed opportunity, as many visitors leave without experiencing DUMBO’s broader offerings.\u003C/p>\n\u003Cp>\u003Cimg src=\"/public/components/groups/dumbo/Washington St.JPG\" alt=\"washington\">\u003C/p>\n\u003Cp>Meanwhile, several potentially vibrant public spaces throughout the district sit underutilized. Areas like Dock Street, Anchorage Plaza, and the York Street subway entrance lack distinctive identity and programming, appearing as “dead zones” to visitors with no compelling reason to linger. These spaces have tremendous potential for activation through strategic interventions such as seating, public art, and temporary markets that could transform them into worthy destinations.\u003C/p>\n\u003Cp>The absence of an intuitive wayfinding system compounds these issues. Without clear signage or suggested routes, visitors struggle to discover attractions beyond Washington Street. Cultural venues, local businesses, and alternative viewpoints remain hidden gems, unknown to most tourists who visit. This navigation challenge prevents organic exploration and limits economic benefits from spreading throughout the neighborhood.\u003C/p>\n\u003Cp>Ultimately, DUMBO’s fundamental challenge is a disconnected visitor experience where scenic spots, shops, and cultural sites exist in isolation rather than as part of a cohesive journey. This fragmentation stems from a mismatch between the neighborhood’s potential (its diverse assets) and current perception (as a single-photo destination). Our interventions, therefore, focus on redistributing visitor density, enhancing physical and digital connectivity, and creating compelling reasons for exploration throughout the district.\u003C/p>\n\u003Ch1 id=\"transformation-analysis\">Transformation Analysis\u003C/h1>\n\u003Cp>Based on our insights, our transformation aims at addressing DUMBO’s issues of tourist congestion, underutilized public spaces, and fragmented visitor experiences. We proposed two main transformations: the DUMBO discovery trail and streetscape enhancements.\u003C/p>\n\u003Cp>The first transformation is the creation of the DUMBO discovery trail. This is a self-guided walking path that links scenic views, cultural landmarks, small businesses, and art installations. The aim of this transformation is to disperse tourists beyond Washington Street by offering an intuitive, enriched, and more comprehensive exploration experience. There will be navigational signage and markers with QR codes to offer navigation assistance, historical context. There will also be seasonal themes (such as food, art, or heritage) that will encourage repeat visits. More importantly, the trail will also be integrated into major digital mapping platforms (e.g., Google Maps, Apple Maps), so visitors naturally encounter the trail when they open their apps in DUMBO. This multi-layered approach both physically and digitally weaves together DUMBO’s diverse attractions into a more cohesive journey that highlights DUMBO’s artistic characteristics and supports local business, while dispersing the tourist traffic on Washington Street.\u003C/p>\n\u003Cp>The second transformation focuses on streetscape enhancements in underused areas such as Dock Street, Anchorage Plaza, Water &#x26; Adams Street, and the York Street Subway entrance. These spaces currently lack comfort, events, and do not look as appealing as other areas in DUMBO. The streetscape enhancements include widening sidewalks, adding seating, integrating more planters, and creating flexible open spaces for rotating public art, performances, and markets. The design language will draw from DUMBO’s industrial heritage, using cobblestones, and materials like weathered steel and bricks, to ensure that improvements reinforce the neighborhood’s unique industrial identity. Furthermore, the addition of more art pieces will help reinforce DUMBO’s identity as a creative district. The goal is to make these currently underutilized spaces more comfortable, visually cohesive, and attractive to both visitors and residents, effectively transforming “dead zones” into vibrant secondary destinations.\u003C/p>\n\u003Cp>Together, these transformations aim to redistribute foot traffic across DUMBO, enhance visitor engagement, support local businesses, and reinforce the area’s cultural and historical character, creating a richer and more sustainable urban experience.\u003C/p>\n\u003Ch1 id=\"prediction-analysis\">Prediction Analysis\u003C/h1>\n\u003Cp>To evaluate the effectiveness of our proposed crowd intervention strategies, we developed an agent-based simulation model using the GAMA platform to replicate tourist movement patterns in the DUMBO area. In the simulation, tourists enter the neighborhood from predefined entry points such as the subway station or Brooklyn Bridge, and proceed to explore the area based on their assigned behavioral profiles. Some tourists head directly to popular photo spots like the Manhattan Bridge, while others wander more randomly or follow interest-based paths. The model integrates real-world spatial data, including shapefiles for roads and buildings, and incorporates network-based pathfinding to ensure realistic movement along streets. By comparing scenarios with and without interventions—such as the addition of new attractions—we assessed the impact of these strategies on crowd distribution. The simulation results demonstrate that our intervention significantly dispersed tourist flows, reducing congestion at overly crowded landmarks and promoting a more balanced spatial distribution.\u003C/p>\n\u003Ch1 id=\"consensus-analysis\">Consensus Analysis\u003C/h1>\n\u003Ch2 id=\"stakeholder-survey-engagement\">Stakeholder Survey Engagement\u003C/h2>\n\u003Cp>To evaluate our transformation proposals with real stakeholders, we conducted on-site fieldwork in DUMBO again and asked 40 participants to do a survey. The participants included visitors, local business owners, and residents. The main part of the survey was to evaluate current and transformed spaces based on the before-and-after images.\u003C/p>\n\u003Cp>The survey results strongly validated our design direction. Transformed locations consistently received higher appeal scores than their current state. For example, the Water &#x26; Adams area improvement shows the most dramatic increase (from 2.9 to 4.5 on a 5-point scale). The majority of participants expressed a preference for wandering and exploring different parts of DUMBO rather than visiting only the famous photo spot, supporting our Discovery Trail concept.\u003C/p>\n\u003Cp>We also gained valuable insights into visitor types, with the data showing a diverse mix of sightseers (30.8%), culture and history enthusiasts (15.4%), food explorers (10.3%), and other categories that help calibrate our activation strategies. This real-world feedback provided empirical support for our hypothesis that visitors would enjoy a more distributed experience throughout DUMBO if appropriate infrastructure and wayfinding were in place.\u003C/p>\n\u003Cp>The survey data will serve as a powerful communication tool in our broader consensus-building efforts. We can present visual preference results to the DUMBO BID and NYC agencies to demonstrate public support, share tourist type data with local businesses to highlight economic benefits, and use the findings as a baseline for continued engagement throughout implementation.\u003C/p>\n\u003Ch2 id=\"broader-stakeholder-strategy\">Broader Stakeholder Strategy\u003C/h2>\n\u003Cp>Beyond our survey work, we identified key stakeholders whose input and support are essential for successful implementation, including:\u003C/p>\n\u003Cul>\n\u003Cli>DUMBO BID: Core implementation partner; coordinates with businesses, manages public space programming\u003C/li>\n\u003Cli>NYC DOT &#x26; DCP: Infrastructure approvals, street design changes, signage, and sidewalk updates\u003C/li>\n\u003Cli>Local Business Owners: Can help offer incentives, co-host events\u003C/li>\n\u003Cli>Residents: Community stewards vital for long-term support and maintenance\u003C/li>\n\u003Cli>Tourists &#x26; Visitors: End users whose behavior drives the success of the public space enhancements\u003C/li>\n\u003C/ul>\n\u003Cp>Our collaborative process will follow a four-stage approach:\u003C/p>\n\u003Cul>\n\u003Cli>Share &#x26; Visualize the Proposal: Present the Insight, Transformation, and Prediction narrative using visuals to make ideas clear for all audiences\u003C/li>\n\u003Cli>Engage Stakeholders in Dialogue: Host workshops to gather input and surface priorities\u003C/li>\n\u003Cli>Collect Public Feedback: Use QR codes, surveys, and comment boards at proposed sites\u003C/li>\n\u003Cli>Prioritize &#x26; Adapt: Synthesize feedback to refine proposals and create a shared action plan\u003C/li>\n\u003C/ul>\n\u003Ch2 id=\"additional-resources\">Additional Resources\u003C/h2>\n\u003Cul>\n\u003Cli>\u003Ca href=\"https://dumbo.org/\">DUMBO Improvement District Website\u003C/a>\u003C/li>\n\u003Cli>\u003Ca href=\"https://dumbo.org/annual-reports/\">Annual Report (PDF)\u003C/a>\u003C/li>\n\u003Cli>\u003Ca href=\"https://www1.nyc.gov/site/sbs/neighborhoods/business-improvement-districts.page\">NYC Small Business Services - BID Directory\u003C/a>\u003C/li>\n\u003C/ul>",{"headings":154,"imagePaths":166,"frontmatter":167},[155,156,157,158,159,162,165],{"depth":50,"slug":51,"text":52},{"depth":50,"slug":54,"text":55},{"depth":50,"slug":57,"text":58},{"depth":50,"slug":60,"text":61},{"depth":63,"slug":160,"text":161},"stakeholder-survey-engagement","Stakeholder Survey Engagement",{"depth":63,"slug":163,"text":164},"broader-stakeholder-strategy","Broader Stakeholder Strategy",{"depth":63,"slug":64,"text":65},[],{"title":124,"description":125,"publishDate":168,"updatedDate":169,"thumbnail":43,"bidName":128,"borough":20,"yearEstablished":21,"featured":22,"draft":70,"revisionMode":22,"tags":170,"insightComponents":171,"transformationComponents":172,"predictionComponents":173,"consensusComponents":174,"dataSource":145,"visualizationTechniques":175},["Date","2023-09-25T00:00:00.000Z"],["Date","2023-10-10T00:00:00.000Z"],[130,131,132,133],[135,136],[138],[140,141],[143,144],[35,36,37,38],"dumbo.md","long-island-city",{"id":177,"data":179,"body":197,"filePath":198,"assetImports":199,"digest":200,"rendered":201,"legacyId":220},{"title":180,"description":181,"publishDate":182,"updatedDate":183,"thumbnail":18,"bidName":180,"borough":184,"yearEstablished":185,"featured":22,"revisionMode":22,"tags":186,"insightComponents":190,"transformationComponents":191,"predictionComponents":192,"consensusComponents":193,"dataSource":194,"visualizationTechniques":195},"Long Island City Partnership","Analysis of the Long Island City Partnership, an area undergoing rapid transformation in Queens.",["Date","2023-10-05T00:00:00.000Z"],["Date","2023-10-20T00:00:00.000Z"],"Queens",2005,[187,188,132,189],"Mixed-Use Development","Arts District","Innovation Hub",[],[],[],[],"NYC Open Data, Long Island City Partnership Annual Reports, Census Data, Real Estate Market Data, Arts Organization Data, MTA Ridership",[35,36,37,38,196],"Development Tracking","The Long Island City Partnership serves one of New York City's fastest-growing and most dynamic neighborhoods. Located on the western edge of Queens directly across from Midtown Manhattan, Long Island City has undergone a remarkable transformation from an industrial center to a vibrant mixed-use district. The BID supports a diverse array of businesses, cultural institutions, and an expanding residential population. With its distinctive waterfront, world-class arts organizations like MoMA PS1, and rapidly changing skyline, Long Island City represents one of the most dramatic urban transformations in recent New York City history.\r\n\r\n# Insight Analysis\r\n\r\nLorem ipsum dolor sit amet, consectetur adipiscing elit. Nulla facilisi. Proin eget fermentum nisi. Vestibulum ante ipsum primis in faucibus orci luctus et ultrices posuere cubilia curae; Donec euismod, nisl eget aliquam ultricies, nunc sapien ultricies arcu, vel feugiat nunc nisl eget libero. Vivamus commodo tortor ac quam varius, in accumsan nulla rutrum. Mauris egestas erat sit amet augue volutpat, eu convallis odio tincidunt. Nulla facilisi. Praesent luctus urna sed dolor congue dictum. Maecenas dignissim eros at nisi varius, in lacinia velit pulvinar.\r\n\r\nPellentesque habitant morbi tristique senectus et netus et malesuada fames ac turpis egestas. In hac habitasse platea dictumst. Proin sed finibus justo. Praesent ultrices dolor non fermentum blandit. Quisque vel congue magna, at varius ligula. Aliquam erat volutpat. Aenean vestibulum metus nec enim consequat, id maximus dolor dignissim. Nullam vehicula tristique eros, non cursus purus elementum ac. Mauris tempus erat purus, sit amet feugiat enim fermentum non.\r\n\r\n# Transformation Analysis\r\n\r\nLorem ipsum dolor sit amet, consectetur adipiscing elit. Sed eget neque at metus aliquam convallis. Nam finibus convallis felis, eu faucibus neque. Vestibulum gravida diam at ipsum posuere, ut pulvinar purus malesuada. Integer gravida fringilla arcu a fermentum. Nullam faucibus dui augue, a imperdiet magna gravida ut. Donec ac justo et enim tempus gravida at quis quam. Duis eu dapibus nisi, a fermentum quam. Mauris nec leo sit amet elit gravida egestas vel at magna. Nulla nisi neque, iaculis in augue eget, lacinia sodales nisl.\r\n\r\nMauris faucibus risus eget libero facilisis, non sagittis urna gravida. Sed feugiat justo odio, non mollis massa efficitur ac. Vestibulum ante ipsum primis in faucibus orci luctus et ultrices posuere cubilia curae; Pellentesque vulputate dictum dolor, eget vestibulum magna volutpat at. Cras a tellus velit. Nam nisi libero, aliquet at facilisis at, consequat nec purus. Sed tincidunt ligula eget placerat rutrum. Praesent pharetra congue purus, eu consequat nisl. Pellentesque euismod, mauris id ultrices efficitur, erat purus imperdiet magna, sit amet sollicitudin turpis ante id lacus.\r\n\r\n# Prediction Analysis\r\n\r\nLorem ipsum dolor sit amet, consectetur adipiscing elit. Sed feugiat lacus ut justo elementum, efficitur sollicitudin nulla volutpat. In hac habitasse platea dictumst. Ut varius at arcu vel vestibulum. Quisque congue magna a ligula elementum, sit amet eleifend eros rutrum. Donec eu nisi eu tortor posuere dictum. Quisque et fringilla justo. Nullam nec auctor nisi. Donec ornare nibh vel consequat tempus. Aliquam laoreet diam turpis, non aliquet libero convallis in. Sed facilisis, velit nec gravida dapibus, dolor felis tincidunt diam, non sagittis est nisi eget ex. Nullam eget semper erat. Vivamus viverra ac enim at tempor. Vestibulum id tellus at velit rhoncus tincidunt sed ut magna.\r\n\r\nCurabitur tincidunt felis quis dui fermentum, eget tristique erat interdum. Mauris vel leo semper, facilisis ligula vitae, porta risus. Duis facilisis purus vel ipsum maximus, nec sagittis magna facilisis. Sed arcu magna, rhoncus nec congue ut, finibus sed diam. Ut sodales tellus non ornare tempus. Donec at felis pellentesque, malesuada neque posuere, ultrices sem. Nam pharetra sapien sed eros congue, in tincidunt nisl semper. Fusce porta felis in risus molestie, vel placerat mauris facilisis.\r\n\r\n# Consensus Analysis\r\n\r\nLorem ipsum dolor sit amet, consectetur adipiscing elit. Donec et tortor eget magna consequat tincidunt. Phasellus neque nulla, finibus ac sollicitudin non, convallis vel nisi. Etiam auctor placerat faucibus. Ut vitae mollis ante, et tempus mauris. Quisque ac urna purus. Aliquam vulputate molestie lectus, non volutpat risus vehicula luctus. Aenean ac quam eu purus eleifend placerat at eget diam. Morbi dapibus at elit in convallis. Mauris posuere leo quam, vitae fringilla leo tempor vel. Ut quis mi porta, suscipit ligula ac, consequat leo. Cras id imperdiet lectus. Aenean quis arcu nisi. Nulla vel nisl eu eros finibus auctor ac ut urna. Suspendisse ac luctus arcu.\r\n\r\nDonec vitae justo vitae turpis rutrum vestibulum vel at tortor. Aliquam quis tellus ut quam viverra fermentum in vitae nulla. Sed mattis accumsan libero, vel sollicitudin ante fringilla at. Nulla facilisi. Duis dignissim varius est, nec dignissim eros. Nullam orci risus, fermentum eu faucibus sit amet, laoreet quis eros. Proin bibendum, metus id bibendum pretium, quam urna dapibus leo, eget tempor magna sem at purus. Praesent faucibus dui id varius elementum. Sed consectetur, orci id rhoncus eleifend, enim magna pellentesque ante, et ornare lectus diam sit amet diam. Integer at magna et arcu iaculis consectetur at dictum lacus.\r\n\r\n## Additional Resources\r\n\r\n- [Long Island City Partnership Website](https://longislandcityqueens.com/)\r\n- [Annual Report (PDF)](https://longislandcityqueens.com/about/annual-reports/)\r\n- [NYC Small Business Services - BID Directory](https://www1.nyc.gov/site/sbs/neighborhoods/business-improvement-districts.page)","src/content/projects/long-island-city.md",[43],"9a8229abf48837f6",{"html":202,"metadata":203},"\u003Cp>The Long Island City Partnership serves one of New York City’s fastest-growing and most dynamic neighborhoods. Located on the western edge of Queens directly across from Midtown Manhattan, Long Island City has undergone a remarkable transformation from an industrial center to a vibrant mixed-use district. The BID supports a diverse array of businesses, cultural institutions, and an expanding residential population. With its distinctive waterfront, world-class arts organizations like MoMA PS1, and rapidly changing skyline, Long Island City represents one of the most dramatic urban transformations in recent New York City history.\u003C/p>\n\u003Ch1 id=\"insight-analysis\">Insight Analysis\u003C/h1>\n\u003Cp>Lorem ipsum dolor sit amet, consectetur adipiscing elit. Nulla facilisi. Proin eget fermentum nisi. Vestibulum ante ipsum primis in faucibus orci luctus et ultrices posuere cubilia curae; Donec euismod, nisl eget aliquam ultricies, nunc sapien ultricies arcu, vel feugiat nunc nisl eget libero. Vivamus commodo tortor ac quam varius, in accumsan nulla rutrum. Mauris egestas erat sit amet augue volutpat, eu convallis odio tincidunt. Nulla facilisi. Praesent luctus urna sed dolor congue dictum. Maecenas dignissim eros at nisi varius, in lacinia velit pulvinar.\u003C/p>\n\u003Cp>Pellentesque habitant morbi tristique senectus et netus et malesuada fames ac turpis egestas. In hac habitasse platea dictumst. Proin sed finibus justo. Praesent ultrices dolor non fermentum blandit. Quisque vel congue magna, at varius ligula. Aliquam erat volutpat. Aenean vestibulum metus nec enim consequat, id maximus dolor dignissim. Nullam vehicula tristique eros, non cursus purus elementum ac. Mauris tempus erat purus, sit amet feugiat enim fermentum non.\u003C/p>\n\u003Ch1 id=\"transformation-analysis\">Transformation Analysis\u003C/h1>\n\u003Cp>Lorem ipsum dolor sit amet, consectetur adipiscing elit. Sed eget neque at metus aliquam convallis. Nam finibus convallis felis, eu faucibus neque. Vestibulum gravida diam at ipsum posuere, ut pulvinar purus malesuada. Integer gravida fringilla arcu a fermentum. Nullam faucibus dui augue, a imperdiet magna gravida ut. Donec ac justo et enim tempus gravida at quis quam. Duis eu dapibus nisi, a fermentum quam. Mauris nec leo sit amet elit gravida egestas vel at magna. Nulla nisi neque, iaculis in augue eget, lacinia sodales nisl.\u003C/p>\n\u003Cp>Mauris faucibus risus eget libero facilisis, non sagittis urna gravida. Sed feugiat justo odio, non mollis massa efficitur ac. Vestibulum ante ipsum primis in faucibus orci luctus et ultrices posuere cubilia curae; Pellentesque vulputate dictum dolor, eget vestibulum magna volutpat at. Cras a tellus velit. Nam nisi libero, aliquet at facilisis at, consequat nec purus. Sed tincidunt ligula eget placerat rutrum. Praesent pharetra congue purus, eu consequat nisl. Pellentesque euismod, mauris id ultrices efficitur, erat purus imperdiet magna, sit amet sollicitudin turpis ante id lacus.\u003C/p>\n\u003Ch1 id=\"prediction-analysis\">Prediction Analysis\u003C/h1>\n\u003Cp>Lorem ipsum dolor sit amet, consectetur adipiscing elit. Sed feugiat lacus ut justo elementum, efficitur sollicitudin nulla volutpat. In hac habitasse platea dictumst. Ut varius at arcu vel vestibulum. Quisque congue magna a ligula elementum, sit amet eleifend eros rutrum. Donec eu nisi eu tortor posuere dictum. Quisque et fringilla justo. Nullam nec auctor nisi. Donec ornare nibh vel consequat tempus. Aliquam laoreet diam turpis, non aliquet libero convallis in. Sed facilisis, velit nec gravida dapibus, dolor felis tincidunt diam, non sagittis est nisi eget ex. Nullam eget semper erat. Vivamus viverra ac enim at tempor. Vestibulum id tellus at velit rhoncus tincidunt sed ut magna.\u003C/p>\n\u003Cp>Curabitur tincidunt felis quis dui fermentum, eget tristique erat interdum. Mauris vel leo semper, facilisis ligula vitae, porta risus. Duis facilisis purus vel ipsum maximus, nec sagittis magna facilisis. Sed arcu magna, rhoncus nec congue ut, finibus sed diam. Ut sodales tellus non ornare tempus. Donec at felis pellentesque, malesuada neque posuere, ultrices sem. Nam pharetra sapien sed eros congue, in tincidunt nisl semper. Fusce porta felis in risus molestie, vel placerat mauris facilisis.\u003C/p>\n\u003Ch1 id=\"consensus-analysis\">Consensus Analysis\u003C/h1>\n\u003Cp>Lorem ipsum dolor sit amet, consectetur adipiscing elit. Donec et tortor eget magna consequat tincidunt. Phasellus neque nulla, finibus ac sollicitudin non, convallis vel nisi. Etiam auctor placerat faucibus. Ut vitae mollis ante, et tempus mauris. Quisque ac urna purus. Aliquam vulputate molestie lectus, non volutpat risus vehicula luctus. Aenean ac quam eu purus eleifend placerat at eget diam. Morbi dapibus at elit in convallis. Mauris posuere leo quam, vitae fringilla leo tempor vel. Ut quis mi porta, suscipit ligula ac, consequat leo. Cras id imperdiet lectus. Aenean quis arcu nisi. Nulla vel nisl eu eros finibus auctor ac ut urna. Suspendisse ac luctus arcu.\u003C/p>\n\u003Cp>Donec vitae justo vitae turpis rutrum vestibulum vel at tortor. Aliquam quis tellus ut quam viverra fermentum in vitae nulla. Sed mattis accumsan libero, vel sollicitudin ante fringilla at. Nulla facilisi. Duis dignissim varius est, nec dignissim eros. Nullam orci risus, fermentum eu faucibus sit amet, laoreet quis eros. Proin bibendum, metus id bibendum pretium, quam urna dapibus leo, eget tempor magna sem at purus. Praesent faucibus dui id varius elementum. Sed consectetur, orci id rhoncus eleifend, enim magna pellentesque ante, et ornare lectus diam sit amet diam. Integer at magna et arcu iaculis consectetur at dictum lacus.\u003C/p>\n\u003Ch2 id=\"additional-resources\">Additional Resources\u003C/h2>\n\u003Cul>\n\u003Cli>\u003Ca href=\"https://longislandcityqueens.com/\">Long Island City Partnership Website\u003C/a>\u003C/li>\n\u003Cli>\u003Ca href=\"https://longislandcityqueens.com/about/annual-reports/\">Annual Report (PDF)\u003C/a>\u003C/li>\n\u003Cli>\u003Ca href=\"https://www1.nyc.gov/site/sbs/neighborhoods/business-improvement-districts.page\">NYC Small Business Services - BID Directory\u003C/a>\u003C/li>\n\u003C/ul>",{"headings":204,"imagePaths":210,"frontmatter":211},[205,206,207,208,209],{"depth":50,"slug":51,"text":52},{"depth":50,"slug":54,"text":55},{"depth":50,"slug":57,"text":58},{"depth":50,"slug":60,"text":61},{"depth":63,"slug":64,"text":65},[],{"title":180,"description":181,"publishDate":212,"updatedDate":213,"thumbnail":43,"bidName":180,"borough":184,"yearEstablished":185,"featured":22,"draft":70,"revisionMode":22,"tags":214,"insightComponents":215,"transformationComponents":216,"predictionComponents":217,"consensusComponents":218,"dataSource":194,"visualizationTechniques":219},["Date","2023-10-05T00:00:00.000Z"],["Date","2023-10-20T00:00:00.000Z"],[187,188,132,189],[],[],[],[],[35,36,37,38,196],"long-island-city.md","robotability",{"id":221,"data":223,"body":251,"filePath":252,"assetImports":253,"digest":254,"rendered":255,"legacyId":276},{"title":224,"description":225,"publishDate":226,"updatedDate":227,"thumbnail":18,"bidName":228,"borough":229,"yearEstablished":230,"featured":22,"revisionMode":22,"tags":231,"insightComponents":237,"transformationComponents":239,"predictionComponents":241,"consensusComponents":242,"dataSource":245,"visualizationTechniques":246},"[DEMO] Robotability Project","Analysis of urban space robotability and its implications for urban planning and design.",["Date","2023-11-01T00:00:00.000Z"],["Date","2023-11-15T00:00:00.000Z"],"34th Street Partnership","Manhattan",2023,[232,233,234,235,236],"Robotics","Urban Design","Accessibility","Smart Cities","Automation",[238],"src/components/groups/_matt_demo/RobotabilityMap.jsx",[240],"/components/groups/_matt_demo/robo_1.png",[],[243,244],"/components/groups/_matt_demo/robo_0.png","https://www.youtube.com/embed/o52MZ1AHyjA","Urban spatial data, Robot navigation metrics, Accessibility maps, Street network data",[37,247,248,249,250],"Heatmaps","Network Analysis","Accessibility Scoring","Comparative Urbanism","The Robotability Project explores the concept of \"robotability\" in urban environments - the degree to which urban spaces are navigable and functional for robotic systems. This research examines how physical urban characteristics affect robot mobility, considering factors like street width, surface conditions, obstacles, and crowd density. The findings have significant implications for urban planning, design policies, and the future integration of autonomous systems in cities.\r\n\r\n# Insight Analysis\r\n\r\nThe robotability of urban spaces varies significantly across different city typologies and neighborhood designs. Initial mapping reveals that areas designed with wide sidewalks, regular street grids, and modern infrastructure tend to score higher on robotability metrics. Historic districts with narrow streets, irregular paths, and frequent level changes present substantial challenges for robotic navigation. These insights highlight how urban morphology, originally designed exclusively for human use, creates an uneven landscape for technological adaptation.\r\n\r\nData collection across multiple urban environments shows significant correlation between robotability scores and factors such as sidewalk width, obstacle density, surface regularity, and pedestrian traffic patterns. The analysis identifies \"robotability deserts\" - areas where physical constraints severely limit robot operation - which often overlap with older neighborhoods and economically disadvantaged areas, raising important questions about technological equity in the urban context.\r\n\r\n# Transformation Analysis\r\n\r\nThe concept of robotability is transforming approaches to urban design and infrastructure planning. Cities considering autonomous delivery systems, cleaning robots, and other automated services are beginning to incorporate robotability assessments into their planning processes. This represents a significant shift from exclusively human-centered design to a more hybridized approach that considers both human and robotic users of public space.\r\n\r\nCase studies show early adaptation strategies, including the creation of \"robot lanes\" in certain commercial districts, standardization of curb cuts, and deployment of navigation beacons in complex environments. These interventions demonstrate how the physical urban environment is being modified to accommodate technological systems, creating new patterns of spatial organization and use that were unanticipated in traditional urban planning frameworks.\r\n\r\n# Prediction Analysis\r\n\r\nFuture urban development will likely see increased emphasis on robotability as autonomous systems become more prevalent in everyday urban life. Models predict that without intentional planning, robotability divides may deepen between newer and older urban areas, creating uneven access to automated services. This could result in technological investment concentrating in already advantaged neighborhoods, while areas with poor robotability metrics might face relative disinvestment.\r\n\r\nPredictive scenarios suggest that cities face key decision points about whether to adapt existing urban fabric to robots, adapt robots to existing urban complexity, or pursue a hybrid approach. Each pathway carries different implications for municipal budgeting, equity concerns, and preservation of urban character. The analysis suggests that early policy interventions could significantly shape these outcomes, potentially avoiding the entrenchment of spatial technological disparities.\r\n\r\n# Consensus Analysis\r\n\r\nStakeholder interviews reveal tensions between technological optimists who see improved robotability as necessary progress and those concerned about prioritizing machine-readable spaces over human experience. Urban designers, technologists, disability advocates, and preservation communities each approach robotability with different priorities and concerns, though consensus exists around the need for transparent evaluation metrics and inclusive planning processes.\r\n\r\nThe emerging consensus suggests that robotability should be considered as one factor within a holistic approach to urban design rather than an overriding priority. Successful examples demonstrate how robotability improvements can align with other urban goals, including accessibility for people with disabilities, pedestrian safety, and environmental sustainability. These integrated approaches offer the most promising direction for incorporating robotability considerations into urban governance structures.\r\n\r\n## Additional Resources\r\n\r\n- [Robotability Research Center](https://example.org/robotability)\r\n- [Urban Robotics Policy Framework (PDF)](https://example.org/urban-robotics-policy.pdf)\r\n- [Mapping Robot Accessibility in Cities Project](https://example.org/mapping-project)\r\n- [International Standards for Robot-Inclusive Urban Design](https://example.org/standards)","src/content/projects/robotability.md",[43],"1be6967fb09da9f2",{"html":256,"metadata":257},"\u003Cp>The Robotability Project explores the concept of “robotability” in urban environments - the degree to which urban spaces are navigable and functional for robotic systems. This research examines how physical urban characteristics affect robot mobility, considering factors like street width, surface conditions, obstacles, and crowd density. The findings have significant implications for urban planning, design policies, and the future integration of autonomous systems in cities.\u003C/p>\n\u003Ch1 id=\"insight-analysis\">Insight Analysis\u003C/h1>\n\u003Cp>The robotability of urban spaces varies significantly across different city typologies and neighborhood designs. Initial mapping reveals that areas designed with wide sidewalks, regular street grids, and modern infrastructure tend to score higher on robotability metrics. Historic districts with narrow streets, irregular paths, and frequent level changes present substantial challenges for robotic navigation. These insights highlight how urban morphology, originally designed exclusively for human use, creates an uneven landscape for technological adaptation.\u003C/p>\n\u003Cp>Data collection across multiple urban environments shows significant correlation between robotability scores and factors such as sidewalk width, obstacle density, surface regularity, and pedestrian traffic patterns. The analysis identifies “robotability deserts” - areas where physical constraints severely limit robot operation - which often overlap with older neighborhoods and economically disadvantaged areas, raising important questions about technological equity in the urban context.\u003C/p>\n\u003Ch1 id=\"transformation-analysis\">Transformation Analysis\u003C/h1>\n\u003Cp>The concept of robotability is transforming approaches to urban design and infrastructure planning. Cities considering autonomous delivery systems, cleaning robots, and other automated services are beginning to incorporate robotability assessments into their planning processes. This represents a significant shift from exclusively human-centered design to a more hybridized approach that considers both human and robotic users of public space.\u003C/p>\n\u003Cp>Case studies show early adaptation strategies, including the creation of “robot lanes” in certain commercial districts, standardization of curb cuts, and deployment of navigation beacons in complex environments. These interventions demonstrate how the physical urban environment is being modified to accommodate technological systems, creating new patterns of spatial organization and use that were unanticipated in traditional urban planning frameworks.\u003C/p>\n\u003Ch1 id=\"prediction-analysis\">Prediction Analysis\u003C/h1>\n\u003Cp>Future urban development will likely see increased emphasis on robotability as autonomous systems become more prevalent in everyday urban life. Models predict that without intentional planning, robotability divides may deepen between newer and older urban areas, creating uneven access to automated services. This could result in technological investment concentrating in already advantaged neighborhoods, while areas with poor robotability metrics might face relative disinvestment.\u003C/p>\n\u003Cp>Predictive scenarios suggest that cities face key decision points about whether to adapt existing urban fabric to robots, adapt robots to existing urban complexity, or pursue a hybrid approach. Each pathway carries different implications for municipal budgeting, equity concerns, and preservation of urban character. The analysis suggests that early policy interventions could significantly shape these outcomes, potentially avoiding the entrenchment of spatial technological disparities.\u003C/p>\n\u003Ch1 id=\"consensus-analysis\">Consensus Analysis\u003C/h1>\n\u003Cp>Stakeholder interviews reveal tensions between technological optimists who see improved robotability as necessary progress and those concerned about prioritizing machine-readable spaces over human experience. Urban designers, technologists, disability advocates, and preservation communities each approach robotability with different priorities and concerns, though consensus exists around the need for transparent evaluation metrics and inclusive planning processes.\u003C/p>\n\u003Cp>The emerging consensus suggests that robotability should be considered as one factor within a holistic approach to urban design rather than an overriding priority. Successful examples demonstrate how robotability improvements can align with other urban goals, including accessibility for people with disabilities, pedestrian safety, and environmental sustainability. These integrated approaches offer the most promising direction for incorporating robotability considerations into urban governance structures.\u003C/p>\n\u003Ch2 id=\"additional-resources\">Additional Resources\u003C/h2>\n\u003Cul>\n\u003Cli>\u003Ca href=\"https://example.org/robotability\">Robotability Research Center\u003C/a>\u003C/li>\n\u003Cli>\u003Ca href=\"https://example.org/urban-robotics-policy.pdf\">Urban Robotics Policy Framework (PDF)\u003C/a>\u003C/li>\n\u003Cli>\u003Ca href=\"https://example.org/mapping-project\">Mapping Robot Accessibility in Cities Project\u003C/a>\u003C/li>\n\u003Cli>\u003Ca href=\"https://example.org/standards\">International Standards for Robot-Inclusive Urban Design\u003C/a>\u003C/li>\n\u003C/ul>",{"headings":258,"imagePaths":264,"frontmatter":265},[259,260,261,262,263],{"depth":50,"slug":51,"text":52},{"depth":50,"slug":54,"text":55},{"depth":50,"slug":57,"text":58},{"depth":50,"slug":60,"text":61},{"depth":63,"slug":64,"text":65},[],{"title":224,"description":225,"publishDate":266,"updatedDate":267,"thumbnail":43,"bidName":228,"borough":229,"projectName":268,"location":269,"yearEstablished":230,"featured":22,"draft":70,"revisionMode":22,"tags":270,"insightComponents":271,"transformationComponents":272,"predictionComponents":273,"consensusComponents":274,"dataSource":245,"visualizationTechniques":275},["Date","2023-11-01T00:00:00.000Z"],["Date","2023-11-15T00:00:00.000Z"],"Robotability Project","Urban Environments",[232,233,234,235,236],[238],[240],[],[243,244],[37,247,248,249,250],"robotability.md","west-village",{"id":277,"data":279,"body":297,"filePath":298,"assetImports":299,"digest":300,"rendered":301,"legacyId":330},{"title":280,"description":281,"publishDate":282,"updatedDate":283,"thumbnail":18,"bidName":284,"borough":229,"yearEstablished":285,"featured":22,"revisionMode":22,"tags":286,"insightComponents":290,"transformationComponents":292,"predictionComponents":293,"consensusComponents":294,"dataSource":295,"visualizationTechniques":296},"West Village BID","Analysis of the West Village Business Improvement District in Manhattan.",["Date","2023-09-20T00:00:00.000Z"],["Date","2023-10-05T00:00:00.000Z"],"West Village",2007,[287,88,288,289],"Historic District","Tourism","Cultural Heritage",[291],"WestVillageStreetView",[],[],[],"NYC Open Data, West Village BID Annual Reports, Census Data, Tourism Statistics",[35,36,37],"The West Village Business Improvement District serves one of Manhattan's most iconic and historic neighborhoods. Established in 2007, the BID supports local businesses in an area known for its distinctive architectural character, winding streets, and vibrant mix of shops, restaurants, and cultural venues. The district encompasses several blocks of primarily commercial streets within the larger West Village neighborhood.\r\n\r\n# Insight Analysis\r\n\r\n## West Village BID - Insight\r\n\r\nWest Village BID, established in 2022, is the fourth newest business improvement district in New York City. Covering approximately 46 acres (0.07 square miles), it is relatively small compared to other major city districts. With a moderate annual budget of around $595,000, the BID mainly focuses on providing essential services such as sanitation and public safety. Situated within the historic Greenwich Village Historic District, an area celebrated for its rich cultural and architectural legacy, West Village BID is surrounded by older, well-established BIDs like the Village Alliance (founded in 1993) and the Union Square Partnership (founded in 1984).\r\n\r\n### Key Observations\r\n- **Land Use**: Predominantly mixed residential and commercial buildings, with higher density toward the north.\r\n- **Mobility**: 7th Avenue South serves as a major traffic corridor, while Bleecker Street and Christopher Street are more pedestrian-focused.\r\n- **Public Spaces**: Parks like Father Demo Square and the Stonewall National Monument serve as important community spaces.\r\n\r\n### Challenges Identified\r\n- **Sanitation**: Garbage pickup was reduced during the pandemic and has only recently returned to pre-pandemic levels; maintaining cleanliness remains a priority.\r\n- **Pedestrian Experience**: Narrow sidewalks in parts of the district combined with heavy foot traffic pose challenges for walkability.\r\n- **Business Dynamics**: Restaurants, boutique shops, and cultural venues experience varying levels of activity, with concerns related to safety and sanitation expressed during interviews.\r\n\r\n# Transformation Analysis\r\n\r\nLorem ipsum dolor sit amet, consectetur adipiscing elit. Sed eget neque at metus aliquam convallis. Nam finibus convallis felis, eu faucibus neque. Vestibulum gravida diam at ipsum posuere, ut pulvinar purus malesuada. Integer gravida fringilla arcu a fermentum. Nullam faucibus dui augue, a imperdiet magna gravida ut. Donec ac justo et enim tempus gravida at quis quam. Duis eu dapibus nisi, a fermentum quam. Mauris nec leo sit amet elit gravida egestas vel at magna. Nulla nisi neque, iaculis in augue eget, lacinia sodales nisl.\r\n\r\nMauris faucibus risus eget libero facilisis, non sagittis urna gravida. Sed feugiat justo odio, non mollis massa efficitur ac. Vestibulum ante ipsum primis in faucibus orci luctus et ultrices posuere cubilia curae; Pellentesque vulputate dictum dolor, eget vestibulum magna volutpat at. Cras a tellus velit. Nam nisi libero, aliquet at facilisis at, consequat nec purus. Sed tincidunt ligula eget placerat rutrum. Praesent pharetra congue purus, eu consequat nisl. Pellentesque euismod, mauris id ultrices efficitur, erat purus imperdiet magna, sit amet sollicitudin turpis ante id lacus.\r\n\r\n# Prediction Analysis\r\n\r\nLorem ipsum dolor sit amet, consectetur adipiscing elit. Sed feugiat lacus ut justo elementum, efficitur sollicitudin nulla volutpat. In hac habitasse platea dictumst. Ut varius at arcu vel vestibulum. Quisque congue magna a ligula elementum, sit amet eleifend eros rutrum. Donec eu nisi eu tortor posuere dictum. Quisque et fringilla justo. Nullam nec auctor nisi. Donec ornare nibh vel consequat tempus. Aliquam laoreet diam turpis, non aliquet libero convallis in. Sed facilisis, velit nec gravida dapibus, dolor felis tincidunt diam, non sagittis est nisi eget ex. Nullam eget semper erat. Vivamus viverra ac enim at tempor. Vestibulum id tellus at velit rhoncus tincidunt sed ut magna.\r\n\r\nCurabitur tincidunt felis quis dui fermentum, eget tristique erat interdum. Mauris vel leo semper, facilisis ligula vitae, porta risus. Duis facilisis purus vel ipsum maximus, nec sagittis magna facilisis. Sed arcu magna, rhoncus nec congue ut, finibus sed diam. Ut sodales tellus non ornare tempus. Donec at felis pellentesque, malesuada neque posuere, ultrices sem. Nam pharetra sapien sed eros congue, in tincidunt nisl semper. Fusce porta felis in risus molestie, vel placerat mauris facilisis.\r\n\r\n# Consensus Analysis\r\n\r\nLorem ipsum dolor sit amet, consectetur adipiscing elit. Donec et tortor eget magna consequat tincidunt. Phasellus neque nulla, finibus ac sollicitudin non, convallis vel nisi. Etiam auctor placerat faucibus. Ut vitae mollis ante, et tempus mauris. Quisque ac urna purus. Aliquam vulputate molestie lectus, non volutpat risus vehicula luctus. Aenean ac quam eu purus eleifend placerat at eget diam. Morbi dapibus at elit in convallis. Mauris posuere leo quam, vitae fringilla leo tempor vel. Ut quis mi porta, suscipit ligula ac, consequat leo. Cras id imperdiet lectus. Aenean quis arcu nisi. Nulla vel nisl eu eros finibus auctor ac ut urna. Suspendisse ac luctus arcu.\r\n\r\nDonec vitae justo vitae turpis rutrum vestibulum vel at tortor. Aliquam quis tellus ut quam viverra fermentum in vitae nulla. Sed mattis accumsan libero, vel sollicitudin ante fringilla at. Nulla facilisi. Duis dignissim varius est, nec dignissim eros. Nullam orci risus, fermentum eu faucibus sit amet, laoreet quis eros. Proin bibendum, metus id bibendum pretium, quam urna dapibus leo, eget tempor magna sem at purus. Praesent faucibus dui id varius elementum. Sed consectetur, orci id rhoncus eleifend, enim magna pellentesque ante, et ornare lectus diam sit amet diam. Integer at magna et arcu iaculis consectetur at dictum lacus.\r\n\r\n## Additional Resources\r\n\r\n- [West Village BID Website](https://westvillagebid.org/)\r\n- [Annual Report (PDF)](https://westvillagebid.org/annual-reports/)\r\n- [NYC Small Business Services - BID Directory](https://www1.nyc.gov/site/sbs/neighborhoods/business-improvement-districts.page)","src/content/projects/west-village.md",[43],"b2d4ff14ee2b4b24",{"html":302,"metadata":303},"\u003Cp>The West Village Business Improvement District serves one of Manhattan’s most iconic and historic neighborhoods. Established in 2007, the BID supports local businesses in an area known for its distinctive architectural character, winding streets, and vibrant mix of shops, restaurants, and cultural venues. The district encompasses several blocks of primarily commercial streets within the larger West Village neighborhood.\u003C/p>\n\u003Ch1 id=\"insight-analysis\">Insight Analysis\u003C/h1>\n\u003Ch2 id=\"west-village-bid---insight\">West Village BID - Insight\u003C/h2>\n\u003Cp>West Village BID, established in 2022, is the fourth newest business improvement district in New York City. Covering approximately 46 acres (0.07 square miles), it is relatively small compared to other major city districts. With a moderate annual budget of around $595,000, the BID mainly focuses on providing essential services such as sanitation and public safety. Situated within the historic Greenwich Village Historic District, an area celebrated for its rich cultural and architectural legacy, West Village BID is surrounded by older, well-established BIDs like the Village Alliance (founded in 1993) and the Union Square Partnership (founded in 1984).\u003C/p>\n\u003Ch3 id=\"key-observations\">Key Observations\u003C/h3>\n\u003Cul>\n\u003Cli>\u003Cstrong>Land Use\u003C/strong>: Predominantly mixed residential and commercial buildings, with higher density toward the north.\u003C/li>\n\u003Cli>\u003Cstrong>Mobility\u003C/strong>: 7th Avenue South serves as a major traffic corridor, while Bleecker Street and Christopher Street are more pedestrian-focused.\u003C/li>\n\u003Cli>\u003Cstrong>Public Spaces\u003C/strong>: Parks like Father Demo Square and the Stonewall National Monument serve as important community spaces.\u003C/li>\n\u003C/ul>\n\u003Ch3 id=\"challenges-identified\">Challenges Identified\u003C/h3>\n\u003Cul>\n\u003Cli>\u003Cstrong>Sanitation\u003C/strong>: Garbage pickup was reduced during the pandemic and has only recently returned to pre-pandemic levels; maintaining cleanliness remains a priority.\u003C/li>\n\u003Cli>\u003Cstrong>Pedestrian Experience\u003C/strong>: Narrow sidewalks in parts of the district combined with heavy foot traffic pose challenges for walkability.\u003C/li>\n\u003Cli>\u003Cstrong>Business Dynamics\u003C/strong>: Restaurants, boutique shops, and cultural venues experience varying levels of activity, with concerns related to safety and sanitation expressed during interviews.\u003C/li>\n\u003C/ul>\n\u003Ch1 id=\"transformation-analysis\">Transformation Analysis\u003C/h1>\n\u003Cp>Lorem ipsum dolor sit amet, consectetur adipiscing elit. Sed eget neque at metus aliquam convallis. Nam finibus convallis felis, eu faucibus neque. Vestibulum gravida diam at ipsum posuere, ut pulvinar purus malesuada. Integer gravida fringilla arcu a fermentum. Nullam faucibus dui augue, a imperdiet magna gravida ut. Donec ac justo et enim tempus gravida at quis quam. Duis eu dapibus nisi, a fermentum quam. Mauris nec leo sit amet elit gravida egestas vel at magna. Nulla nisi neque, iaculis in augue eget, lacinia sodales nisl.\u003C/p>\n\u003Cp>Mauris faucibus risus eget libero facilisis, non sagittis urna gravida. Sed feugiat justo odio, non mollis massa efficitur ac. Vestibulum ante ipsum primis in faucibus orci luctus et ultrices posuere cubilia curae; Pellentesque vulputate dictum dolor, eget vestibulum magna volutpat at. Cras a tellus velit. Nam nisi libero, aliquet at facilisis at, consequat nec purus. Sed tincidunt ligula eget placerat rutrum. Praesent pharetra congue purus, eu consequat nisl. Pellentesque euismod, mauris id ultrices efficitur, erat purus imperdiet magna, sit amet sollicitudin turpis ante id lacus.\u003C/p>\n\u003Ch1 id=\"prediction-analysis\">Prediction Analysis\u003C/h1>\n\u003Cp>Lorem ipsum dolor sit amet, consectetur adipiscing elit. Sed feugiat lacus ut justo elementum, efficitur sollicitudin nulla volutpat. In hac habitasse platea dictumst. Ut varius at arcu vel vestibulum. Quisque congue magna a ligula elementum, sit amet eleifend eros rutrum. Donec eu nisi eu tortor posuere dictum. Quisque et fringilla justo. Nullam nec auctor nisi. Donec ornare nibh vel consequat tempus. Aliquam laoreet diam turpis, non aliquet libero convallis in. Sed facilisis, velit nec gravida dapibus, dolor felis tincidunt diam, non sagittis est nisi eget ex. Nullam eget semper erat. Vivamus viverra ac enim at tempor. Vestibulum id tellus at velit rhoncus tincidunt sed ut magna.\u003C/p>\n\u003Cp>Curabitur tincidunt felis quis dui fermentum, eget tristique erat interdum. Mauris vel leo semper, facilisis ligula vitae, porta risus. Duis facilisis purus vel ipsum maximus, nec sagittis magna facilisis. Sed arcu magna, rhoncus nec congue ut, finibus sed diam. Ut sodales tellus non ornare tempus. Donec at felis pellentesque, malesuada neque posuere, ultrices sem. Nam pharetra sapien sed eros congue, in tincidunt nisl semper. Fusce porta felis in risus molestie, vel placerat mauris facilisis.\u003C/p>\n\u003Ch1 id=\"consensus-analysis\">Consensus Analysis\u003C/h1>\n\u003Cp>Lorem ipsum dolor sit amet, consectetur adipiscing elit. Donec et tortor eget magna consequat tincidunt. Phasellus neque nulla, finibus ac sollicitudin non, convallis vel nisi. Etiam auctor placerat faucibus. Ut vitae mollis ante, et tempus mauris. Quisque ac urna purus. Aliquam vulputate molestie lectus, non volutpat risus vehicula luctus. Aenean ac quam eu purus eleifend placerat at eget diam. Morbi dapibus at elit in convallis. Mauris posuere leo quam, vitae fringilla leo tempor vel. Ut quis mi porta, suscipit ligula ac, consequat leo. Cras id imperdiet lectus. Aenean quis arcu nisi. Nulla vel nisl eu eros finibus auctor ac ut urna. Suspendisse ac luctus arcu.\u003C/p>\n\u003Cp>Donec vitae justo vitae turpis rutrum vestibulum vel at tortor. Aliquam quis tellus ut quam viverra fermentum in vitae nulla. Sed mattis accumsan libero, vel sollicitudin ante fringilla at. Nulla facilisi. Duis dignissim varius est, nec dignissim eros. Nullam orci risus, fermentum eu faucibus sit amet, laoreet quis eros. Proin bibendum, metus id bibendum pretium, quam urna dapibus leo, eget tempor magna sem at purus. Praesent faucibus dui id varius elementum. Sed consectetur, orci id rhoncus eleifend, enim magna pellentesque ante, et ornare lectus diam sit amet diam. Integer at magna et arcu iaculis consectetur at dictum lacus.\u003C/p>\n\u003Ch2 id=\"additional-resources\">Additional Resources\u003C/h2>\n\u003Cul>\n\u003Cli>\u003Ca href=\"https://westvillagebid.org/\">West Village BID Website\u003C/a>\u003C/li>\n\u003Cli>\u003Ca href=\"https://westvillagebid.org/annual-reports/\">Annual Report (PDF)\u003C/a>\u003C/li>\n\u003Cli>\u003Ca href=\"https://www1.nyc.gov/site/sbs/neighborhoods/business-improvement-districts.page\">NYC Small Business Services - BID Directory\u003C/a>\u003C/li>\n\u003C/ul>",{"headings":304,"imagePaths":320,"frontmatter":321},[305,306,309,313,316,317,318,319],{"depth":50,"slug":51,"text":52},{"depth":63,"slug":307,"text":308},"west-village-bid---insight","West Village BID - Insight",{"depth":310,"slug":311,"text":312},3,"key-observations","Key Observations",{"depth":310,"slug":314,"text":315},"challenges-identified","Challenges Identified",{"depth":50,"slug":54,"text":55},{"depth":50,"slug":57,"text":58},{"depth":50,"slug":60,"text":61},{"depth":63,"slug":64,"text":65},[],{"title":280,"description":281,"publishDate":322,"updatedDate":323,"thumbnail":43,"bidName":284,"borough":229,"yearEstablished":285,"featured":22,"draft":70,"revisionMode":22,"tags":324,"insightComponents":325,"transformationComponents":326,"predictionComponents":327,"consensusComponents":328,"dataSource":295,"visualizationTechniques":329},["Date","2023-09-20T00:00:00.000Z"],["Date","2023-10-05T00:00:00.000Z"],[287,88,288,289],[291],[],[],[],[35,36,37],"west-village.md"]